[
    {
        "id": "cd3d2e0244da",
        "course": "newbridge",
        "race_time": "15-Aug-25",
        "race_type": "Greyhound Meeting",
        "utc_datetime": null,
        "local_time": "15-Aug-25",
        "timezone_name": "Europe/Dublin",
        "field_size": 0,
        "country": "IRE",
        "discipline": "greyhound",
        "source_file": "grireland_meetings.html",
        "race_url": "https://www.grireland.ie/racing/upcoming-race-cards/upcoming-race-card-summary/?track=NWB&id=112350&date=15-Aug-2025",
        "runners": [],
        "favorite": null,
        "second_favorite": null,
        "value_score": 0.0,
        "data_sources": [
            "grireland_meetings.html"
        ]
    },
    {
        "id": "2f23079a9b27",
        "course": "dundalk",
        "race_time": "15-Aug-25",
        "race_type": "Greyhound Meeting",
        "utc_datetime": null,
        "local_time": "15-Aug-25",
        "timezone_name": "Europe/Dublin",
        "field_size": 0,
        "country": "IRE",
        "discipline": "greyhound",
        "source_file": "grireland_meetings.html",
        "race_url": "https://www.grireland.ie/racing/upcoming-race-cards/upcoming-race-card-summary/?track=DLK&id=112367&date=15-Aug-2025",
        "runners": [],
        "favorite": null,
        "second_favorite": null,
        "value_score": 0.0,
        "data_sources": [
            "grireland_meetings.html"
        ]
    },
    {
        "id": "a5aeca9b1f84",
        "course": "curraheen",
        "race_time": "15-Aug-25",
        "race_type": "Greyhound Meeting",
        "utc_datetime": null,
        "local_time": "15-Aug-25",
        "timezone_name": "Europe/Dublin",
        "field_size": 0,
        "country": "IRE",
        "discipline": "greyhound",
        "source_file": "grireland_meetings.html",
        "race_url": "https://www.grireland.ie/racing/upcoming-race-cards/upcoming-race-card-summary/?track=CRK&id=112440&date=15-Aug-2025",
        "runners": [],
        "favorite": null,
        "second_favorite": null,
        "value_score": 0.0,
        "data_sources": [
            "grireland_meetings.html"
        ]
    },
    {
        "id": "8fa951408319",
        "course": "tralee",
        "race_time": "15-Aug-25",
        "race_type": "Greyhound Meeting",
        "utc_datetime": null,
        "local_time": "15-Aug-25",
        "timezone_name": "Europe/Dublin",
        "field_size": 0,
        "country": "IRE",
        "discipline": "greyhound",
        "source_file": "grireland_meetings.html",
        "race_url": "https://www.grireland.ie/racing/upcoming-race-cards/upcoming-race-card-summary/?track=TRL&id=112443&date=15-Aug-2025",
        "runners": [],
        "favorite": null,
        "second_favorite": null,
        "value_score": 0.0,
        "data_sources": [
            "grireland_meetings.html"
        ]
    },
    {
        "id": "662857dffd69",
        "course": "galway",
        "race_time": "15-Aug-25",
        "race_type": "Greyhound Meeting",
        "utc_datetime": null,
        "local_time": "15-Aug-25",
        "timezone_name": "Europe/Dublin",
        "field_size": 0,
        "country": "IRE",
        "discipline": "greyhound",
        "source_file": "grireland_meetings.html",
        "race_url": "https://www.grireland.ie/racing/upcoming-race-cards/upcoming-race-card-summary/?track=GLY&id=112452&date=15-Aug-2025",
        "runners": [],
        "favorite": null,
        "second_favorite": null,
        "value_score": 0.0,
        "data_sources": [
            "grireland_meetings.html"
        ]
    },
    {
        "id": "554e025e3ea4",
        "course": "shelbourne",
        "race_time": "15-Aug-25",
        "race_type": "Greyhound Meeting",
        "utc_datetime": null,
        "local_time": "15-Aug-25",
        "timezone_name": "Europe/Dublin",
        "field_size": 0,
        "country": "IRE",
        "discipline": "greyhound",
        "source_file": "grireland_meetings.html",
        "race_url": "https://www.grireland.ie/racing/upcoming-race-cards/upcoming-race-card-summary/?track=SPK&id=112464&date=15-Aug-2025",
        "runners": [],
        "favorite": null,
        "second_favorite": null,
        "value_score": 0.0,
        "data_sources": [
            "grireland_meetings.html"
        ]
    },
    {
        "id": "cd6fc26c8706",
        "course": "mullingar",
        "race_time": "15-Aug-25",
        "race_type": "Greyhound Meeting",
        "utc_datetime": null,
        "local_time": "15-Aug-25",
        "timezone_name": "Europe/Dublin",
        "field_size": 0,
        "country": "IRE",
        "discipline": "greyhound",
        "source_file": "grireland_meetings.html",
        "race_url": "https://www.grireland.ie/racing/upcoming-race-cards/upcoming-race-card-summary/?track=MGR&id=112467&date=15-Aug-2025",
        "runners": [],
        "favorite": null,
        "second_favorite": null,
        "value_score": 0.0,
        "data_sources": [
            "grireland_meetings.html"
        ]
    },
    {
        "id": "9b010230672d",
        "course": "clonmel",
        "race_time": "15-Aug-25",
        "race_type": "Greyhound Meeting",
        "utc_datetime": null,
        "local_time": "15-Aug-25",
        "timezone_name": "Europe/Dublin",
        "field_size": 0,
        "country": "IRE",
        "discipline": "greyhound",
        "source_file": "grireland_meetings.html",
        "race_url": "https://www.grireland.ie/racing/upcoming-race-cards/upcoming-race-card-summary/?track=CML&id=112470&date=15-Aug-2025",
        "runners": [],
        "favorite": null,
        "second_favorite": null,
        "value_score": 0.0,
        "data_sources": [
            "grireland_meetings.html"
        ]
    },
    {
        "id": "5de1d1535b6f",
        "course": "kilkenny",
        "race_time": "15-Aug-25",
        "race_type": "Greyhound Meeting",
        "utc_datetime": null,
        "local_time": "15-Aug-25",
        "timezone_name": "Europe/Dublin",
        "field_size": 0,
        "country": "IRE",
        "discipline": "greyhound",
        "source_file": "grireland_meetings.html",
        "race_url": "https://www.grireland.ie/racing/upcoming-race-cards/upcoming-race-card-summary/?track=KKY&id=112472&date=15-Aug-2025",
        "runners": [],
        "favorite": null,
        "second_favorite": null,
        "value_score": 0.0,
        "data_sources": [
            "grireland_meetings.html"
        ]
    },
    {
        "id": "580780c2ba0a",
        "course": "thurles",
        "race_time": "16-Aug-25",
        "race_type": "Greyhound Meeting",
        "utc_datetime": null,
        "local_time": "16-Aug-25",
        "timezone_name": "Europe/Dublin",
        "field_size": 0,
        "country": "IRE",
        "discipline": "greyhound",
        "source_file": "grireland_meetings.html",
        "race_url": "https://www.grireland.ie/racing/upcoming-race-cards/upcoming-race-card-summary/?track=THR&id=112474&date=16-Aug-2025",
        "runners": [],
        "favorite": null,
        "second_favorite": null,
        "value_score": 0.0,
        "data_sources": [
            "grireland_meetings.html"
        ]
    },
    {
        "id": "9e6719687fc5",
        "course": "youghal",
        "race_time": "16-Aug-25",
        "race_type": "Greyhound Meeting",
        "utc_datetime": null,
        "local_time": "16-Aug-25",
        "timezone_name": "Europe/Dublin",
        "field_size": 0,
        "country": "IRE",
        "discipline": "greyhound",
        "source_file": "grireland_meetings.html",
        "race_url": "https://www.grireland.ie/racing/upcoming-race-cards/upcoming-race-card-summary/?track=YGL&id=112475&date=16-Aug-2025",
        "runners": [],
        "favorite": null,
        "second_favorite": null,
        "value_score": 0.0,
        "data_sources": [
            "grireland_meetings.html"
        ]
    },
    {
        "id": "3cb21f072f12",
        "course": "shelbourne",
        "race_time": "16-Aug-25",
        "race_type": "Greyhound Meeting",
        "utc_datetime": null,
        "local_time": "16-Aug-25",
        "timezone_name": "Europe/Dublin",
        "field_size": 0,
        "country": "IRE",
        "discipline": "greyhound",
        "source_file": "grireland_meetings.html",
        "race_url": "https://www.grireland.ie/racing/upcoming-race-cards/upcoming-race-card-summary/?track=SPK&id=112477&date=16-Aug-2025",
        "runners": [],
        "favorite": null,
        "second_favorite": null,
        "value_score": 0.0,
        "data_sources": [
            "grireland_meetings.html"
        ]
    },
    {
        "id": "ee9ce9400e1c",
        "course": "lifford",
        "race_time": "16-Aug-25",
        "race_type": "Greyhound Meeting",
        "utc_datetime": null,
        "local_time": "16-Aug-25",
        "timezone_name": "Europe/Dublin",
        "field_size": 0,
        "country": "IRE",
        "discipline": "greyhound",
        "source_file": "grireland_meetings.html",
        "race_url": "https://www.grireland.ie/racing/upcoming-race-cards/upcoming-race-card-summary/?track=LFD&id=112483&date=16-Aug-2025",
        "runners": [],
        "favorite": null,
        "second_favorite": null,
        "value_score": 0.0,
        "data_sources": [
            "grireland_meetings.html"
        ]
    },
    {
        "id": "d4a69becf0b7",
        "course": "waterford",
        "race_time": "16-Aug-25",
        "race_type": "Greyhound Meeting",
        "utc_datetime": null,
        "local_time": "16-Aug-25",
        "timezone_name": "Europe/Dublin",
        "field_size": 0,
        "country": "IRE",
        "discipline": "greyhound",
        "source_file": "grireland_meetings.html",
        "race_url": "https://www.grireland.ie/racing/upcoming-race-cards/upcoming-race-card-summary/?track=WFD&id=112463&date=16-Aug-2025",
        "runners": [],
        "favorite": null,
        "second_favorite": null,
        "value_score": 0.0,
        "data_sources": [
            "grireland_meetings.html"
        ]
    },
    {
        "id": "968d8ccd4d65",
        "course": "mullingar",
        "race_time": "16-Aug-25",
        "race_type": "Greyhound Meeting",
        "utc_datetime": null,
        "local_time": "16-Aug-25",
        "timezone_name": "Europe/Dublin",
        "field_size": 0,
        "country": "IRE",
        "discipline": "greyhound",
        "source_file": "grireland_meetings.html",
        "race_url": "https://www.grireland.ie/racing/upcoming-race-cards/upcoming-race-card-summary/?track=MGR&id=112465&date=16-Aug-2025",
        "runners": [],
        "favorite": null,
        "second_favorite": null,
        "value_score": 0.0,
        "data_sources": [
            "grireland_meetings.html"
        ]
    },
    {
        "id": "28bc889e28d2",
        "course": "drumbo",
        "race_time": "16-Aug-25",
        "race_type": "Greyhound Meeting",
        "utc_datetime": null,
        "local_time": "16-Aug-25",
        "timezone_name": "Europe/Dublin",
        "field_size": 0,
        "country": "IRE",
        "discipline": "greyhound",
        "source_file": "grireland_meetings.html",
        "race_url": "https://www.grireland.ie/racing/upcoming-race-cards/upcoming-race-card-summary/?track=DBP&id=112466&date=16-Aug-2025",
        "runners": [],
        "favorite": null,
        "second_favorite": null,
        "value_score": 0.0,
        "data_sources": [
            "grireland_meetings.html"
        ]
    },
    {
        "id": "8a867bab73ad",
        "course": "tralee",
        "race_time": "16-Aug-25",
        "race_type": "Greyhound Meeting",
        "utc_datetime": null,
        "local_time": "16-Aug-25",
        "timezone_name": "Europe/Dublin",
        "field_size": 0,
        "country": "IRE",
        "discipline": "greyhound",
        "source_file": "grireland_meetings.html",
        "race_url": "https://www.grireland.ie/racing/upcoming-race-cards/upcoming-race-card-summary/?track=TRL&id=112444&date=16-Aug-2025",
        "runners": [],
        "favorite": null,
        "second_favorite": null,
        "value_score": 0.0,
        "data_sources": [
            "grireland_meetings.html"
        ]
    },
    {
        "id": "b0779d677c86",
        "course": "dundalk",
        "race_time": "16-Aug-25",
        "race_type": "Greyhound Meeting",
        "utc_datetime": null,
        "local_time": "16-Aug-25",
        "timezone_name": "Europe/Dublin",
        "field_size": 0,
        "country": "IRE",
        "discipline": "greyhound",
        "source_file": "grireland_meetings.html",
        "race_url": "https://www.grireland.ie/racing/upcoming-race-cards/upcoming-race-card-summary/?track=DLK&id=112447&date=16-Aug-2025",
        "runners": [],
        "favorite": null,
        "second_favorite": null,
        "value_score": 0.0,
        "data_sources": [
            "grireland_meetings.html"
        ]
    },
    {
        "id": "7a9702542f3b",
        "course": "limerick",
        "race_time": "16-Aug-25",
        "race_type": "Greyhound Meeting",
        "utc_datetime": null,
        "local_time": "16-Aug-25",
        "timezone_name": "Europe/Dublin",
        "field_size": 0,
        "country": "IRE",
        "discipline": "greyhound",
        "source_file": "grireland_meetings.html",
        "race_url": "https://www.grireland.ie/racing/upcoming-race-cards/upcoming-race-card-summary/?track=LMK&id=112450&date=16-Aug-2025",
        "runners": [],
        "favorite": null,
        "second_favorite": null,
        "value_score": 0.0,
        "data_sources": [
            "grireland_meetings.html"
        ]
    },
    {
        "id": "7b3e7d04fbbd",
        "course": "curraheen",
        "race_time": "16-Aug-25",
        "race_type": "Greyhound Meeting",
        "utc_datetime": null,
        "local_time": "16-Aug-25",
        "timezone_name": "Europe/Dublin",
        "field_size": 0,
        "country": "IRE",
        "discipline": "greyhound",
        "source_file": "grireland_meetings.html",
        "race_url": "https://www.grireland.ie/racing/upcoming-race-cards/upcoming-race-card-summary/?track=CRK&id=112441&date=16-Aug-2025",
        "runners": [],
        "favorite": null,
        "second_favorite": null,
        "value_score": 0.0,
        "data_sources": [
            "grireland_meetings.html"
        ]
    },
    {
        "id": "eb87074042af",
        "course": "clonmel",
        "race_time": "17-Aug-25",
        "race_type": "Greyhound Meeting",
        "utc_datetime": null,
        "local_time": "17-Aug-25",
        "timezone_name": "Europe/Dublin",
        "field_size": 0,
        "country": "IRE",
        "discipline": "greyhound",
        "source_file": "grireland_meetings.html",
        "race_url": "https://www.grireland.ie/racing/upcoming-race-cards/upcoming-race-card-summary/?track=CML&id=112471&date=17-Aug-2025",
        "runners": [],
        "favorite": null,
        "second_favorite": null,
        "value_score": 0.0,
        "data_sources": [
            "grireland_meetings.html"
        ]
    },
    {
        "id": "5102f5d0330f",
        "course": "mullingar",
        "race_time": "17-Aug-25",
        "race_type": "Greyhound Meeting",
        "utc_datetime": null,
        "local_time": "17-Aug-25",
        "timezone_name": "Europe/Dublin",
        "field_size": 0,
        "country": "IRE",
        "discipline": "greyhound",
        "source_file": "grireland_meetings.html",
        "race_url": "https://www.grireland.ie/racing/upcoming-race-cards/upcoming-race-card-summary/?track=MGR&id=112468&date=17-Aug-2025",
        "runners": [],
        "favorite": null,
        "second_favorite": null,
        "value_score": 0.0,
        "data_sources": [
            "grireland_meetings.html"
        ]
    },
    {
        "id": "ea1ff65f13d2",
        "course": "lifford",
        "race_time": "17-Aug-25",
        "race_type": "Greyhound Meeting",
        "utc_datetime": null,
        "local_time": "17-Aug-25",
        "timezone_name": "Europe/Dublin",
        "field_size": 0,
        "country": "IRE",
        "discipline": "greyhound",
        "source_file": "grireland_meetings.html",
        "race_url": "https://www.grireland.ie/racing/upcoming-race-cards/upcoming-race-card-summary/?track=LFD&id=112491&date=17-Aug-2025",
        "runners": [],
        "favorite": null,
        "second_favorite": null,
        "value_score": 0.0,
        "data_sources": [
            "grireland_meetings.html"
        ]
    },
    {
        "id": "3dbeb473c1e4",
        "course": "youghal",
        "race_time": "18-Aug-25",
        "race_type": "Greyhound Meeting",
        "utc_datetime": null,
        "local_time": "18-Aug-25",
        "timezone_name": "Europe/Dublin",
        "field_size": 0,
        "country": "IRE",
        "discipline": "greyhound",
        "source_file": "grireland_meetings.html",
        "race_url": "https://www.grireland.ie/racing/upcoming-race-cards/upcoming-race-card-summary/?track=YGL&id=112484&date=18-Aug-2025",
        "runners": [],
        "favorite": null,
        "second_favorite": null,
        "value_score": 0.0,
        "data_sources": [
            "grireland_meetings.html"
        ]
    },
    {
        "id": "544369fdceda",
        "course": "enniscorthy",
        "race_time": "18-Aug-25",
        "race_type": "Greyhound Meeting",
        "utc_datetime": null,
        "local_time": "18-Aug-25",
        "timezone_name": "Europe/Dublin",
        "field_size": 0,
        "country": "IRE",
        "discipline": "greyhound",
        "source_file": "grireland_meetings.html",
        "race_url": "https://www.grireland.ie/racing/upcoming-race-cards/upcoming-race-card-summary/?track=ECY&id=112454&date=18-Aug-2025",
        "runners": [],
        "favorite": null,
        "second_favorite": null,
        "value_score": 0.0,
        "data_sources": [
            "grireland_meetings.html"
        ]
    },
    {
        "id": "d581125b6baa",
        "course": "thurles",
        "race_time": "19-Aug-25",
        "race_type": "Greyhound Meeting",
        "utc_datetime": null,
        "local_time": "19-Aug-25",
        "timezone_name": "Europe/Dublin",
        "field_size": 0,
        "country": "IRE",
        "discipline": "greyhound",
        "source_file": "grireland_meetings.html",
        "race_url": "https://www.grireland.ie/racing/upcoming-race-cards/upcoming-race-card-summary/?track=THR&id=112473&date=19-Aug-2025",
        "runners": [],
        "favorite": null,
        "second_favorite": null,
        "value_score": 0.0,
        "data_sources": [
            "grireland_meetings.html"
        ]
    },
    {
        "id": "462892f07c20",
        "course": "shelbourne",
        "race_time": "21-Aug-25",
        "race_type": "Greyhound Meeting",
        "utc_datetime": null,
        "local_time": "21-Aug-25",
        "timezone_name": "Europe/Dublin",
        "field_size": 0,
        "country": "IRE",
        "discipline": "greyhound",
        "source_file": "grireland_meetings.html",
        "race_url": "https://www.grireland.ie/racing/upcoming-race-cards/upcoming-race-card-summary/?track=SPK&id=112502&date=21-Aug-2025",
        "runners": [],
        "favorite": null,
        "second_favorite": null,
        "value_score": 0.0,
        "data_sources": [
            "grireland_meetings.html"
        ]
    },
    {
        "id": "876376892e66",
        "course": "dundalk",
        "race_time": "22-Aug-25",
        "race_type": "Greyhound Meeting",
        "utc_datetime": null,
        "local_time": "22-Aug-25",
        "timezone_name": "Europe/Dublin",
        "field_size": 0,
        "country": "IRE",
        "discipline": "greyhound",
        "source_file": "grireland_meetings.html",
        "race_url": "https://www.grireland.ie/racing/upcoming-race-cards/upcoming-race-card-summary/?track=DLK&id=112493&date=22-Aug-2025",
        "runners": [],
        "favorite": null,
        "second_favorite": null,
        "value_score": 0.0,
        "data_sources": [
            "grireland_meetings.html"
        ]
    },
    {
        "id": "141074ea38ab",
        "course": "kilkenny",
        "race_time": "22-Aug-25",
        "race_type": "Greyhound Meeting",
        "utc_datetime": null,
        "local_time": "22-Aug-25",
        "timezone_name": "Europe/Dublin",
        "field_size": 0,
        "country": "IRE",
        "discipline": "greyhound",
        "source_file": "grireland_meetings.html",
        "race_url": "https://www.grireland.ie/racing/upcoming-race-cards/upcoming-race-card-summary/?track=KKY&id=112547&date=22-Aug-2025",
        "runners": [],
        "favorite": null,
        "second_favorite": null,
        "value_score": 0.0,
        "data_sources": [
            "grireland_meetings.html"
        ]
    },
    {
        "id": "7b1065c2bf8b",
        "course": "curraheen",
        "race_time": "22-Aug-25",
        "race_type": "Greyhound Meeting",
        "utc_datetime": null,
        "local_time": "22-Aug-25",
        "timezone_name": "Europe/Dublin",
        "field_size": 0,
        "country": "IRE",
        "discipline": "greyhound",
        "source_file": "grireland_meetings.html",
        "race_url": "https://www.grireland.ie/racing/upcoming-race-cards/upcoming-race-card-summary/?track=CRK&id=112548&date=22-Aug-2025",
        "runners": [],
        "favorite": null,
        "second_favorite": null,
        "value_score": 0.0,
        "data_sources": [
            "grireland_meetings.html"
        ]
    },
    {
        "id": "c170609dd751",
        "course": "lifford",
        "race_time": "23-Aug-25",
        "race_type": "Greyhound Meeting",
        "utc_datetime": null,
        "local_time": "23-Aug-25",
        "timezone_name": "Europe/Dublin",
        "field_size": 0,
        "country": "IRE",
        "discipline": "greyhound",
        "source_file": "grireland_meetings.html",
        "race_url": "https://www.grireland.ie/racing/upcoming-race-cards/upcoming-race-card-summary/?track=LFD&id=112499&date=23-Aug-2025",
        "runners": [],
        "favorite": null,
        "second_favorite": null,
        "value_score": 0.0,
        "data_sources": [
            "grireland_meetings.html"
        ]
    },
    {
        "id": "f4604ed1e723",
        "course": "dundalk",
        "race_time": "23-Aug-25",
        "race_type": "Greyhound Meeting",
        "utc_datetime": null,
        "local_time": "23-Aug-25",
        "timezone_name": "Europe/Dublin",
        "field_size": 0,
        "country": "IRE",
        "discipline": "greyhound",
        "source_file": "grireland_meetings.html",
        "race_url": "https://www.grireland.ie/racing/upcoming-race-cards/upcoming-race-card-summary/?track=DLK&id=112492&date=23-Aug-2025",
        "runners": [],
        "favorite": null,
        "second_favorite": null,
        "value_score": 0.0,
        "data_sources": [
            "grireland_meetings.html"
        ]
    },
    {
        "id": "36b77170287b",
        "course": "dundalk",
        "race_time": "06-Sep-25",
        "race_type": "Greyhound Meeting",
        "utc_datetime": null,
        "local_time": "06-Sep-25",
        "timezone_name": "Europe/Dublin",
        "field_size": 0,
        "country": "IRE",
        "discipline": "greyhound",
        "source_file": "grireland_meetings.html",
        "race_url": "https://www.grireland.ie/racing/upcoming-race-cards/upcoming-race-card-summary/?track=DLK&id=112546&date=06-Sep-2025",
        "runners": [],
        "favorite": null,
        "second_favorite": null,
        "value_score": 0.0,
        "data_sources": [
            "grireland_meetings.html"
        ]
    }
]